zxp2gus/__init__.py
zxp2gus/cli.py
zxp2gus/ioUser.py
zxp2gus/zxbasic.py
zxp2gus/zxlib.py
zxp2gus/zxp2png.py
zxp2gus-0.6.dist-info/METADATA
zxp2gus-0.6.dist-info/WHEEL
zxp2gus-0.6.dist-info/entry_points.txt
zxp2gus-0.6.dist-info/top_level.txt
zxp2gus-0.6.dist-info/RECORD
