Metadata-Version: 2.4
Name: zxp2gus
Version: 0.6
Summary: Convert ZX Paintbrush files to GuSprites ZXBasic code
Home-page: https://github.com/rtorralba/zxp2gus
Author: Raül Torralba
Requires-Dist: numpy
Requires-Dist: opencv-python
Requires-Dist: Pillow
Dynamic: author
Dynamic: description
Dynamic: description-content-type
Dynamic: home-page
Dynamic: requires-dist
Dynamic: summary
